open_download_manager/VERSION
open_download_manager/__init__.py
open_download_manager/__main__.py
open_download_manager/base.py
open_download_manager/celery/__init__.py
open_download_manager/celery/download.py
open_download_manager/celery/worker.py
open_download_manager/ext/__init__.py
open_download_manager/ext/admin.py
open_download_manager/ext/auth.py
open_download_manager/ext/bg.py
open_download_manager/ext/commands.py
open_download_manager/ext/database.py
open_download_manager/ext/restapi/__init__.py
open_download_manager/ext/restapi/resources.py
open_download_manager/ext/webui/__init__.py
open_download_manager/ext/webui/static/bulma.min.css
open_download_manager/ext/webui/templates/base.html
open_download_manager/ext/webui/templates/create_download.html
open_download_manager/ext/webui/templates/index.html
open_download_manager/ext/webui/templates/product.html
open_download_manager/ext/webui/views.py
open_download_manager/models.py
open_download_manager-0.1.0.dist-info/LICENSE
open_download_manager-0.1.0.dist-info/METADATA
open_download_manager-0.1.0.dist-info/WHEEL
open_download_manager-0.1.0.dist-info/entry_points.txt
open_download_manager-0.1.0.dist-info/RECORD
