Metadata-Version: 2.1
Name: open-download-manager
Version: 0.1.0
Summary: 
Author: cmmeyer1800
Requires-Python: >=3.10,<4.0
Classifier: Programming Language :: Python :: 3
Classifier: Programming Language :: Python :: 3.10
Classifier: Programming Language :: Python :: 3.11
Classifier: Programming Language :: Python :: 3.12
Requires-Dist: celery (>=5.3.6,<6.0.0)
Requires-Dist: click (>=8.1.7,<9.0.0)
Requires-Dist: dynaconf (>=3.2.4,<4.0.0)
Requires-Dist: flask (>=3.0.0,<4.0.0)
Requires-Dist: flask-admin (>=1.6.1,<2.0.0)
Requires-Dist: flask-bootstrap (>=3.3.7.1,<4.0.0.0)
Requires-Dist: flask-restful (>=0.3.10,<0.4.0)
Requires-Dist: flask-simplelogin (>=0.1.2,<0.2.0)
Requires-Dist: flask-sqlalchemy (>=3.1.1,<4.0.0)
Requires-Dist: redis (>=5.0.1,<6.0.0)
Requires-Dist: sqlalchemy-serializer (>=1.4.1,<2.0.0)
